[{"id": 259, "date": "2026-07-08", "symbol": "DELHIVERY", "timeframe": "Monthly", "pattern": "6M Breakout", "patterns": "[\"Monthly: 6M Breakout\"]", "price": 501.8, "sl": 494.27, "target1": 520.38, "target2": 538.6, "target3": 560.68, "rr": 2.5, "vol_ratio": 0.6, "fno": 1, "tv_link": "https://in.tradingview.com/chart/?symbol=NSE:DELHIVERY"}, {"id": 260, "date": "2026-07-08", "symbol": "PHOENIXLTD", "timeframe": "Monthly", "pattern": "6M Breakout", "patterns": "[\"Weekly: Cup & Handle\", \"Monthly: 6M Breakout\"]", "price": 2022.5, "sl": 1966.39, "target1": 2124.03, "target2": 2124.03, "target3": 2246.94, "rr": 1.8, "vol_ratio": 0.6, "fno": 1, "tv_link": "https://in.tradingview.com/chart/?symbol=NSE:PHOENIXLTD"}, {"id": 261, "date": "2026-07-08", "symbol": "EXIDEIND", "timeframe": "Monthly", "pattern": "6M Breakout", "patterns": "[\"Weekly: Cup & Handle\", \"Monthly: 6M Breakout\"]", "price": 421.4, "sl": 409.61, "target1": 438.95, "target2": 450.69, "target3": 468.3, "rr": 1.5, "vol_ratio": 1.9, "fno": 1, "tv_link": "https://in.tradingview.com/chart/?symbol=NSE:EXIDEIND"}, {"id": 262, "date": "2026-07-08", "symbol": "GRANULES", "timeframe": "Monthly", "pattern": "6M Breakout", "patterns": "[\"Weekly: Cup & Handle\", \"Monthly: 6M Breakout\"]", "price": 859.5, "sl": 835.56, "target1": 895.54, "target2": 919.53, "target3": 955.51, "rr": 1.5, "vol_ratio": 1.3, "fno": 1, "tv_link": "https://in.tradingview.com/chart/?symbol=NSE:GRANULES"}, {"id": 263, "date": "2026-07-08", "symbol": "INDUSINDBK", "timeframe": "Monthly", "pattern": "6M Breakout", "patterns": "[\"Weekly: 20W Breakout\", \"Weekly: Cup & Handle\", \"Monthly: 6M Breakout\"]", "price": 994.7, "sl": 968.58, "target1": 1032.81, "target2": 1059.83, "target3": 1098.94, "rr": 1.5, "vol_ratio": 1.5, "fno": 1, "tv_link": "https://in.tradingview.com/chart/?symbol=NSE:INDUSINDBK"}, {"id": 264, "date": "2026-07-08", "symbol": "JBCHEPHARM", "timeframe": "Monthly", "pattern": "6M Breakout", "patterns": "[\"Daily: 52W Breakout\", \"Weekly: 20W Breakout\", \"Monthly: 6M Breakout\"]", "price": 2435.8, "sl": 2386.41, "target1": 2509.88, "target2": 2559.26, "target3": 2633.34, "rr": 1.5, "vol_ratio": 3.6, "fno": 1, "tv_link": "https://in.tradingview.com/chart/?symbol=NSE:JBCHEPHARM"}, {"id": 265, "date": "2026-07-08", "symbol": "OBEROIRLTY", "timeframe": "Monthly", "pattern": "6M Breakout", "patterns": "[\"Weekly: Cup & Handle\", \"Monthly: 6M Breakout\"]", "price": 1870.1, "sl": 1819.49, "target1": 1946.02, "target2": 1976.17, "target3": 2072.56, "rr": 1.5, "vol_ratio": 0.8, "fno": 1, "tv_link": "https://in.tradingview.com/chart/?symbol=NSE:OBEROIRLTY"}, {"id": 266, "date": "2026-07-08", "symbol": "SONACOMS", "timeframe": "Monthly", "pattern": "6M Breakout", "patterns": "[\"Weekly: Cup & Handle\", \"Monthly: 6M Breakout\"]", "price": 662.0, "sl": 645.38, "target1": 677.4, "target2": 703.72, "target3": 728.72, "rr": 0.9, "vol_ratio": 1.5, "fno": 1, "tv_link": "https://in.tradingview.com/chart/?symbol=NSE:SONACOMS"}, {"id": 267, "date": "2026-07-08", "symbol": "IPCALAB", "timeframe": "Monthly", "pattern": "6M Breakout", "patterns": "[\"Monthly: 6M Breakout\"]", "price": 1762.4, "sl": 1711.98, "target1": 1803.44, "target2": 1888.46, "target3": 1964.09, "rr": 0.8, "vol_ratio": 0.8, "fno": 1, "tv_link": "https://in.tradingview.com/chart/?symbol=NSE:IPCALAB"}, {"id": 268, "date": "2026-07-08", "symbol": "NYKAA", "timeframe": "Monthly", "pattern": "6M Breakout", "patterns": "[\"Weekly: Cup & Handle\", \"Monthly: 6M Breakout\"]", "price": 318.0, "sl": 309.83, "target1": 323.87, "target2": 338.25, "target3": 350.43, "rr": 0.7, "vol_ratio": 1.1, "fno": 1, "tv_link": "https://in.tradingview.com/chart/?symbol=NSE:NYKAA"}, {"id": 269, "date": "2026-07-08", "symbol": "TORNTPHARM", "timeframe": "Monthly", "pattern": "6M Breakout", "patterns": "[\"Monthly: 6M Breakout\"]", "price": 4866.4, "sl": 4765.17, "target1": 4923.26, "target2": 5119.48, "target3": 5271.33, "rr": 0.6, "vol_ratio": 2.0, "fno": 1, "tv_link": "https://in.tradingview.com/chart/?symbol=NSE:TORNTPHARM"}, {"id": 270, "date": "2026-07-08", "symbol": "TRITURBINE", "timeframe": "Weekly", "pattern": "Cup & Handle", "patterns": "[\"Weekly: Cup & Handle\"]", "price": 613.1, "sl": 602.6, "target1": 655.7, "target2": 684.1, "target3": 726.69, "rr": 4.1, "vol_ratio": 0.8, "fno": 1, "tv_link": "https://in.tradingview.com/chart/?symbol=NSE:TRITURBINE"}, {"id": 271, "date": "2026-07-08", "symbol": "USHAMART", "timeframe": "Weekly", "pattern": "Cup & Handle", "patterns": "[\"Weekly: Cup & Handle\"]", "price": 489.6, "sl": 482.19, "target1": 517.25, "target2": 527.79, "target3": 550.68, "rr": 3.7, "vol_ratio": 0.5, "fno": 1, "tv_link": "https://in.tradingview.com/chart/?symbol=NSE:USHAMART"}, {"id": 272, "date": "2026-07-08", "symbol": "CHOLAFIN", "timeframe": "Weekly", "pattern": "Cup & Handle", "patterns": "[\"Weekly: Cup & Handle\"]", "price": 1769.4, "sl": 1742.86, "target1": 1865.62, "target2": 1865.62, "target3": 1956.06, "rr": 3.6, "vol_ratio": 0.9, "fno": 1, "tv_link": "https://in.tradingview.com/chart/?symbol=NSE:CHOLAFIN"}, {"id": 273, "date": "2026-07-08", "symbol": "PAGEIND", "timeframe": "Weekly", "pattern": "Cup & Handle", "patterns": "[\"Weekly: Cup & Handle\"]", "price": 41415.0, "sl": 40793.78, "target1": 43635.72, "target2": 43635.72, "target3": 45806.79, "rr": 3.6, "vol_ratio": 1.9, "fno": 1, "tv_link": "https://in.tradingview.com/chart/?symbol=NSE:PAGEIND"}, {"id": 274, "date": "2026-07-08", "symbol": "WOCKPHARMA", "timeframe": "Weekly", "pattern": "Cup & Handle", "patterns": "[\"Weekly: Cup & Handle\"]", "price": 1824.5, "sl": 1790.76, "target1": 1945.94, "target2": 2026.89, "target3": 2148.33, "rr": 3.6, "vol_ratio": 0.5, "fno": 1, "tv_link": "https://in.tradingview.com/chart/?symbol=NSE:WOCKPHARMA"}, {"id": 275, "date": "2026-07-08", "symbol": "FORTIS", "timeframe": "Weekly", "pattern": "Cup & Handle", "patterns": "[\"Weekly: Cup & Handle\"]", "price": 943.8, "sl": 929.59, "target1": 991.57, "target2": 996.99, "target3": 1034.61, "rr": 3.4, "vol_ratio": 1.4, "fno": 1, "tv_link": "https://in.tradingview.com/chart/?symbol=NSE:FORTIS"}, {"id": 276, "date": "2026-07-08", "symbol": "ZEEL", "timeframe": "Weekly", "pattern": "Cup & Handle", "patterns": "[\"Weekly: Cup & Handle\"]", "price": 99.6, "sl": 97.31, "target1": 107.28, "target2": 112.43, "target3": 120.15, "rr": 3.4, "vol_ratio": 0.5, "fno": 1, "tv_link": "https://in.tradingview.com/chart/?symbol=NSE:ZEEL"}, {"id": 277, "date": "2026-07-08", "symbol": "ADANIGREEN", "timeframe": "Weekly", "pattern": "Cup & Handle", "patterns": "[\"Weekly: Cup & Handle\"]", "price": 1504.6, "sl": 1481.63, "target1": 1581.15, "target2": 1624.34, "target3": 1696.19, "rr": 3.3, "vol_ratio": 1.0, "fno": 1, "tv_link": "https://in.tradingview.com/chart/?symbol=NSE:ADANIGREEN"}, {"id": 278, "date": "2026-07-08", "symbol": "AUROPHARMA", "timeframe": "Weekly", "pattern": "Cup & Handle", "patterns": "[\"Weekly: Cup & Handle\"]", "price": 1557.4, "sl": 1534.04, "target1": 1628.62, "target2": 1628.62, "target3": 1712.35, "rr": 3.0, "vol_ratio": 0.7, "fno": 1, "tv_link": "https://in.tradingview.com/chart/?symbol=NSE:AUROPHARMA"}, {"id": 279, "date": "2026-07-08", "symbol": "DLF", "timeframe": "Weekly", "pattern": "Cup & Handle", "patterns": "[\"Weekly: Cup & Handle\"]", "price": 634.0, "sl": 624.49, "target1": 662.19, "target2": 680.78, "target3": 709.18, "rr": 3.0, "vol_ratio": 1.1, "fno": 1, "tv_link": "https://in.tradingview.com/chart/?symbol=NSE:DLF"}, {"id": 280, "date": "2026-07-08", "symbol": "IDFCFIRSTB", "timeframe": "Weekly", "pattern": "Cup & Handle", "patterns": "[\"Weekly: Cup & Handle\"]", "price": 77.8, "sl": 76.65, "target1": 81.36, "target2": 81.36, "target3": 85.02, "rr": 3.0, "vol_ratio": 0.8, "fno": 1, "tv_link": "https://in.tradingview.com/chart/?symbol=NSE:IDFCFIRSTB"}, {"id": 281, "date": "2026-07-08", "symbol": "IDEA", "timeframe": "Weekly", "pattern": "Cup & Handle", "patterns": "[\"Weekly: Cup & Handle\"]", "price": 13.9, "sl": 13.65, "target1": 14.78, "target2": 15.26, "target3": 15.73, "rr": 3.0, "vol_ratio": 0.9, "fno": 1, "tv_link": "https://in.tradingview.com/chart/?symbol=NSE:IDEA"}, {"id": 282, "date": "2026-07-08", "symbol": "MAXHEALTH", "timeframe": "Weekly", "pattern": "Cup & Handle", "patterns": "[\"Weekly: Cup & Handle\"]", "price": 1084.8, "sl": 1068.53, "target1": 1130.74, "target2": 1162.06, "target3": 1207.31, "rr": 2.8, "vol_ratio": 0.9, "fno": 1, "tv_link": "https://in.tradingview.com/chart/?symbol=NSE:MAXHEALTH"}, {"id": 283, "date": "2026-07-08", "symbol": "BIOCON", "timeframe": "Weekly", "pattern": "Cup & Handle", "patterns": "[\"Weekly: Cup & Handle\"]", "price": 397.0, "sl": 391.09, "target1": 413.29, "target2": 429.59, "target3": 440.36, "rr": 2.7, "vol_ratio": 0.9, "fno": 1, "tv_link": "https://in.tradingview.com/chart/?symbol=NSE:BIOCON"}, {"id": 284, "date": "2026-07-08", "symbol": "MARUTI", "timeframe": "Weekly", "pattern": "Cup & Handle", "patterns": "[\"Weekly: Cup & Handle\"]", "price": 13951.0, "sl": 13741.74, "target1": 14525.01, "target2": 14525.01, "target3": 15264.49, "rr": 2.7, "vol_ratio": 0.9, "fno": 1, "tv_link": "https://in.tradingview.com/chart/?symbol=NSE:MARUTI"}, {"id": 285, "date": "2026-07-08", "symbol": "TRENT", "timeframe": "Weekly", "pattern": "Cup & Handle", "patterns": "[\"Weekly: Cup & Handle\"]", "price": 2924.0, "sl": 2866.63, "target1": 3078.63, "target2": 3181.72, "target3": 3336.35, "rr": 2.7, "vol_ratio": 1.2, "fno": 1, "tv_link": "https://in.tradingview.com/chart/?symbol=NSE:TRENT"}, {"id": 286, "date": "2026-07-08", "symbol": "HINDPETRO", "timeframe": "Weekly", "pattern": "Cup & Handle", "patterns": "[\"Weekly: Cup & Handle\"]", "price": 386.9, "sl": 380.31, "target1": 403.57, "target2": 417.9, "target3": 431.43, "rr": 2.6, "vol_ratio": 2.8, "fno": 1, "tv_link": "https://in.tradingview.com/chart/?symbol=NSE:HINDPETRO"}, {"id": 287, "date": "2026-07-08", "symbol": "BPCL", "timeframe": "Weekly", "pattern": "Cup & Handle", "patterns": "[\"Weekly: Cup & Handle\"]", "price": 303.5, "sl": 297.38, "target1": 319.25, "target2": 319.99, "target3": 335.8, "rr": 2.5, "vol_ratio": 1.9, "fno": 1, "tv_link": "https://in.tradingview.com/chart/?symbol=NSE:BPCL"}, {"id": 288, "date": "2026-07-08", "symbol": "GAIL", "timeframe": "Weekly", "pattern": "Cup & Handle", "patterns": "[\"Weekly: Cup & Handle\"]", "price": 169.2, "sl": 166.7, "target1": 175.61, "target2": 177.58, "target3": 183.26, "rr": 2.5, "vol_ratio": 1.5, "fno": 1, "tv_link": "https://in.tradingview.com/chart/?symbol=NSE:GAIL"}, {"id": 289, "date": "2026-07-08", "symbol": "INDIGO", "timeframe": "Weekly", "pattern": "Cup & Handle", "patterns": "[\"Weekly: Cup & Handle\"]", "price": 5124.0, "sl": 5047.14, "target1": 5313.85, "target2": 5449.12, "target3": 5630.26, "rr": 2.5, "vol_ratio": 1.5, "fno": 1, "tv_link": "https://in.tradingview.com/chart/?symbol=NSE:INDIGO"}, {"id": 290, "date": "2026-07-08", "symbol": "LAURUSLABS", "timeframe": "Weekly", "pattern": "Cup & Handle", "patterns": "[\"Weekly: Cup & Handle\"]", "price": 1469.2, "sl": 1437.79, "target1": 1547.22, "target2": 1547.22, "target3": 1635.76, "rr": 2.5, "vol_ratio": 0.7, "fno": 1, "tv_link": "https://in.tradingview.com/chart/?symbol=NSE:LAURUSLABS"}, {"id": 291, "date": "2026-07-08", "symbol": "POLYCAB", "timeframe": "Weekly", "pattern": "Cup & Handle", "patterns": "[\"Weekly: Cup & Handle\"]", "price": 9234.0, "sl": 9095.49, "target1": 9574.31, "target2": 9801.18, "target3": 10141.49, "rr": 2.5, "vol_ratio": 0.8, "fno": 1, "tv_link": "https://in.tradingview.com/chart/?symbol=NSE:POLYCAB"}, {"id": 292, "date": "2026-07-08", "symbol": "CIPLA", "timeframe": "Weekly", "pattern": "Cup & Handle", "patterns": "[\"Weekly: Cup & Handle\"]", "price": 1431.8, "sl": 1410.32, "target1": 1482.65, "target2": 1482.65, "target3": 1544.13, "rr": 2.4, "vol_ratio": 0.7, "fno": 1, "tv_link": "https://in.tradingview.com/chart/?symbol=NSE:CIPLA"}, {"id": 293, "date": "2026-07-08", "symbol": "SHREECEM", "timeframe": "Weekly", "pattern": "Cup & Handle", "patterns": "[\"Weekly: Cup & Handle\"]", "price": 25910.0, "sl": 25521.35, "target1": 26835.15, "target2": 26835.15, "target3": 28199.85, "rr": 2.4, "vol_ratio": 0.6, "fno": 1, "tv_link": "https://in.tradingview.com/chart/?symbol=NSE:SHREECEM"}, {"id": 294, "date": "2026-07-08", "symbol": "TATACOMM", "timeframe": "Weekly", "pattern": "Cup & Handle", "patterns": "[\"Weekly: Cup & Handle\"]", "price": 1886.2, "sl": 1841.96, "target1": 1987.23, "target2": 2099.45, "target3": 2155.6, "rr": 2.3, "vol_ratio": 0.4, "fno": 1, "tv_link": "https://in.tradingview.com/chart/?symbol=NSE:TATACOMM"}, {"id": 295, "date": "2026-07-08", "symbol": "INDHOTEL", "timeframe": "Weekly", "pattern": "Cup & Handle", "patterns": "[\"Weekly: Cup & Handle\"]", "price": 722.9, "sl": 711.26, "target1": 749.04, "target2": 749.04, "target3": 783.54, "rr": 2.2, "vol_ratio": 0.5, "fno": 1, "tv_link": "https://in.tradingview.com/chart/?symbol=NSE:INDHOTEL"}, {"id": 296, "date": "2026-07-08", "symbol": "ASIANPAINT", "timeframe": "Weekly", "pattern": "Cup & Handle", "patterns": "[\"Weekly: Cup & Handle\"]", "price": 2665.9, "sl": 2625.91, "target1": 2748.59, "target2": 2794.29, "target3": 2871.85, "rr": 2.1, "vol_ratio": 1.2, "fno": 1, "tv_link": "https://in.tradingview.com/chart/?symbol=NSE:ASIANPAINT"}, {"id": 297, "date": "2026-07-08", "symbol": "DRREDDY", "timeframe": "Weekly", "pattern": "Cup & Handle", "patterns": "[\"Weekly: Cup & Handle\"]", "price": 1349.0, "sl": 1321.41, "target1": 1407.83, "target2": 1407.83, "target3": 1470.52, "rr": 2.1, "vol_ratio": 0.9, "fno": 1, "tv_link": "https://in.tradingview.com/chart/?symbol=NSE:DRREDDY"}, {"id": 298, "date": "2026-07-08", "symbol": "PIDILITIND", "timeframe": "Weekly", "pattern": "Cup & Handle", "patterns": "[\"Weekly: Cup & Handle\"]", "price": 1570.4, "sl": 1546.84, "target1": 1618.57, "target2": 1618.57, "target3": 1689.72, "rr": 2.0, "vol_ratio": 0.8, "fno": 1, "tv_link": "https://in.tradingview.com/chart/?symbol=NSE:PIDILITIND"}, {"id": 299, "date": "2026-07-08", "symbol": "OFSS", "timeframe": "Weekly", "pattern": "Cup & Handle", "patterns": "[\"Weekly: Cup & Handle\"]", "price": 11002.0, "sl": 10836.97, "target1": 11303.2, "target2": 11812.96, "target3": 12299.54, "rr": 1.8, "vol_ratio": 0.5, "fno": 1, "tv_link": "https://in.tradingview.com/chart/?symbol=NSE:OFSS"}, {"id": 300, "date": "2026-07-08", "symbol": "EICHERMOT", "timeframe": "Weekly", "pattern": "Cup & Handle", "patterns": "[\"Weekly: Cup & Handle\"]", "price": 7418.5, "sl": 7242.58, "target1": 7715.23, "target2": 7715.23, "target3": 8122.18, "rr": 1.7, "vol_ratio": 1.3, "fno": 1, "tv_link": "https://in.tradingview.com/chart/?symbol=NSE:EICHERMOT"}, {"id": 301, "date": "2026-07-08", "symbol": "BAJFINANCE", "timeframe": "Weekly", "pattern": "Cup & Handle", "patterns": "[\"Weekly: Cup & Handle\"]", "price": 1010.4, "sl": 987.35, "target1": 1047.64, "target2": 1070.91, "target3": 1107.21, "rr": 1.6, "vol_ratio": 0.9, "fno": 1, "tv_link": "https://in.tradingview.com/chart/?symbol=NSE:BAJFINANCE"}, {"id": 302, "date": "2026-07-08", "symbol": "GODREJPROP", "timeframe": "Weekly", "pattern": "Cup & Handle", "patterns": "[\"Weekly: Cup & Handle\"]", "price": 1979.5, "sl": 1932.88, "target1": 2051.49, "target2": 2116.68, "target3": 2198.99, "rr": 1.5, "vol_ratio": 1.5, "fno": 1, "tv_link": "https://in.tradingview.com/chart/?symbol=NSE:GODREJPROP"}, {"id": 303, "date": "2026-07-08", "symbol": "GRASIM", "timeframe": "Weekly", "pattern": "Cup & Handle", "patterns": "[\"Weekly: Cup & Handle\"]", "price": 3134.8, "sl": 3087.78, "target1": 3205.89, "target2": 3205.89, "target3": 3351.76, "rr": 1.5, "vol_ratio": 0.8, "fno": 1, "tv_link": "https://in.tradingview.com/chart/?symbol=NSE:GRASIM"}, {"id": 304, "date": "2026-07-08", "symbol": "NAUKRI", "timeframe": "Weekly", "pattern": "20W Breakout", "patterns": "[\"Weekly: 20W Breakout\"]", "price": 1179.0, "sl": 1139.76, "target1": 1237.87, "target2": 1277.11, "target3": 1335.98, "rr": 1.5, "vol_ratio": 3.8, "fno": 1, "tv_link": "https://in.tradingview.com/chart/?symbol=NSE:NAUKRI"}, {"id": 305, "date": "2026-07-08", "symbol": "MOTHERSON", "timeframe": "Weekly", "pattern": "Cup & Handle", "patterns": "[\"Weekly: Cup & Handle\"]", "price": 140.6, "sl": 136.09, "target1": 147.5, "target2": 154.47, "target3": 158.91, "rr": 1.5, "vol_ratio": 0.8, "fno": 1, "tv_link": "https://in.tradingview.com/chart/?symbol=NSE:MOTHERSON"}, {"id": 306, "date": "2026-07-08", "symbol": "TECHM", "timeframe": "Weekly", "pattern": "Cup & Handle", "patterns": "[\"Weekly: Cup & Handle\"]", "price": 1428.8, "sl": 1386.29, "target1": 1492.57, "target2": 1535.08, "target3": 1598.85, "rr": 1.5, "vol_ratio": 0.6, "fno": 1, "tv_link": "https://in.tradingview.com/chart/?symbol=NSE:TECHM"}, {"id": 307, "date": "2026-07-08", "symbol": "BAJAJFINSV", "timeframe": "Weekly", "pattern": "Cup & Handle", "patterns": "[\"Weekly: Cup & Handle\"]", "price": 1854.9, "sl": 1814.51, "target1": 1906.42, "target2": 1955.88, "target3": 2016.47, "rr": 1.3, "vol_ratio": 1.1, "fno": 1, "tv_link": "https://in.tradingview.com/chart/?symbol=NSE:BAJAJFINSV"}, {"id": 308, "date": "2026-07-08", "symbol": "COFORGE", "timeframe": "Weekly", "pattern": "Cup & Handle", "patterns": "[\"Weekly: Cup & Handle\"]", "price": 1445.9, "sl": 1393.21, "target1": 1515.98, "target2": 1577.62, "target3": 1656.65, "rr": 1.3, "vol_ratio": 0.8, "fno": 1, "tv_link": "https://in.tradingview.com/chart/?symbol=NSE:COFORGE"}, {"id": 309, "date": "2026-07-08", "symbol": "MANAPPURAM", "timeframe": "Weekly", "pattern": "Cup & Handle", "patterns": "[\"Weekly: Cup & Handle\"]", "price": 332.5, "sl": 321.83, "target1": 346.16, "target2": 359.36, "target3": 375.45, "rr": 1.3, "vol_ratio": 0.9, "fno": 1, "tv_link": "https://in.tradingview.com/chart/?symbol=NSE:MANAPPURAM"}, {"id": 310, "date": "2026-07-08", "symbol": "CANFINHOME", "timeframe": "Weekly", "pattern": "Cup & Handle", "patterns": "[\"Weekly: Cup & Handle\"]", "price": 892.3, "sl": 866.76, "target1": 922.37, "target2": 956.15, "target3": 994.47, "rr": 1.2, "vol_ratio": 1.2, "fno": 1, "tv_link": "https://in.tradingview.com/chart/?symbol=NSE:CANFINHOME"}, {"id": 311, "date": "2026-07-08", "symbol": "LALPATHLAB", "timeframe": "Weekly", "pattern": "Cup & Handle", "patterns": "[\"Weekly: Cup & Handle\"]", "price": 1653.5, "sl": 1606.88, "target1": 1709.41, "target2": 1789.66, "target3": 1868.29, "rr": 1.2, "vol_ratio": 0.2, "fno": 1, "tv_link": "https://in.tradingview.com/chart/?symbol=NSE:LALPATHLAB"}, {"id": 312, "date": "2026-07-08", "symbol": "DIVISLAB", "timeframe": "Weekly", "pattern": "Cup & Handle", "patterns": "[\"Weekly: Cup & Handle\"]", "price": 6755.0, "sl": 6616.31, "target1": 6924.2, "target2": 7101.74, "target3": 7309.78, "rr": 1.2, "vol_ratio": 1.1, "fno": 1, "tv_link": "https://in.tradingview.com/chart/?symbol=NSE:DIVISLAB"}, {"id": 313, "date": "2026-07-08", "symbol": "MPHASIS", "timeframe": "Weekly", "pattern": "Cup & Handle", "patterns": "[\"Weekly: Cup & Handle\"]", "price": 2241.9, "sl": 2170.94, "target1": 2328.56, "target2": 2419.31, "target3": 2525.75, "rr": 1.2, "vol_ratio": 1.1, "fno": 1, "tv_link": "https://in.tradingview.com/chart/?symbol=NSE:MPHASIS"}, {"id": 314, "date": "2026-07-08", "symbol": "STARHEALTH", "timeframe": "Weekly", "pattern": "Cup & Handle", "patterns": "[\"Daily: Bull Flag\", \"Weekly: Cup & Handle\"]", "price": 584.2, "sl": 568.27, "target1": 602.77, "target2": 624.46, "target3": 648.61, "rr": 1.2, "vol_ratio": 0.5, "fno": 1, "tv_link": "https://in.tradingview.com/chart/?symbol=NSE:STARHEALTH"}, {"id": 315, "date": "2026-07-08", "symbol": "ALKEM", "timeframe": "Weekly", "pattern": "Cup & Handle", "patterns": "[\"Weekly: Cup & Handle\"]", "price": 5606.0, "sl": 5488.84, "target1": 5706.32, "target2": 5898.9, "target3": 6074.63, "rr": 0.9, "vol_ratio": 0.7, "fno": 1, "tv_link": "https://in.tradingview.com/chart/?symbol=NSE:ALKEM"}, {"id": 316, "date": "2026-07-08", "symbol": "SUNPHARMA", "timeframe": "Weekly", "pattern": "Cup & Handle", "patterns": "[\"Weekly: Cup & Handle\"]", "price": 1888.2, "sl": 1857.87, "target1": 1915.28, "target2": 1964.01, "target3": 2009.5, "rr": 0.9, "vol_ratio": 1.6, "fno": 1, "tv_link": "https://in.tradingview.com/chart/?symbol=NSE:SUNPHARMA"}, {"id": 258, "date": "2026-07-06", "symbol": "MANAPPURAM", "timeframe": "Daily", "pattern": "AI Channel Breakout", "patterns": "[\"AI Channel Breakout\"]", "price": 346.1, "sl": 307.19, "target1": 404.47, "target2": 443.38, "target3": 443.38, "rr": 2.5, "vol_ratio": 3.03, "fno": 1, "tv_link": "https://in.tradingview.com/chart/?symbol=NSE:MANAPPURAM"}, {"id": 229, "date": "2026-06-16", "symbol": "JKCEMENT", "timeframe": "Daily", "pattern": "AI Channel Breakout", "patterns": "[\"AI Channel Breakout\"]", "price": 5314.0, "sl": 4560.16, "target1": 6444.76, "target2": 7198.6, "target3": 7198.6, "rr": 2.5, "vol_ratio": 1.39, "fno": 1, "tv_link": "https://in.tradingview.com/chart/?symbol=NSE:JKCEMENT"}, {"id": 230, "date": "2026-06-16", "symbol": "CHOLAFIN", "timeframe": "Daily", "pattern": "AI Channel Breakout", "patterns": "[\"AI Channel Breakout\"]", "price": 1680.4, "sl": 1466.39, "target1": 2001.42, "target2": 2215.43, "target3": 2215.43, "rr": 2.5, "vol_ratio": 1.33, "fno": 1, "tv_link": "https://in.tradingview.com/chart/?symbol=NSE:CHOLAFIN"}, {"id": 146, "date": "2026-06-13", "symbol": "INDIGO", "timeframe": "Daily", "pattern": "AI Channel Breakout", "patterns": "[\"AI Channel Breakout\"]", "price": 4709.7, "sl": 4239.23, "target1": 5415.41, "target2": 5885.88, "target3": 5885.88, "rr": 2.5, "vol_ratio": 2.46, "fno": 1, "tv_link": "https://in.tradingview.com/chart/?symbol=NSE:INDIGO"}, {"id": 147, "date": "2026-06-13", "symbol": "AUBANK", "timeframe": "Daily", "pattern": "AI Channel Breakout", "patterns": "[\"AI Channel Breakout\"]", "price": 1015.5, "sl": 914.82, "target1": 1166.52, "target2": 1267.2, "target3": 1267.2, "rr": 2.5, "vol_ratio": 2.35, "fno": 1, "tv_link": "https://in.tradingview.com/chart/?symbol=NSE:AUBANK"}, {"id": 148, "date": "2026-06-13", "symbol": "BOSCHLTD", "timeframe": "Daily", "pattern": "AI Channel Breakout", "patterns": "[\"AI Channel Breakout\"]", "price": 39060.0, "sl": 35530.6, "target1": 44354.1, "target2": 47883.5, "target3": 47883.5, "rr": 2.5, "vol_ratio": 1.65, "fno": 1, "tv_link": "https://in.tradingview.com/chart/?symbol=NSE:BOSCHLTD"}, {"id": 149, "date": "2026-06-13", "symbol": "UCOBANK", "timeframe": "Daily", "pattern": "AI Channel Breakout", "patterns": "[\"AI Channel Breakout\"]", "price": 25.99, "sl": 24.21, "target1": 28.66, "target2": 30.44, "target3": 30.44, "rr": 2.5, "vol_ratio": 1.38, "fno": 1, "tv_link": "https://in.tradingview.com/chart/?symbol=NSE:UCOBANK"}, {"id": 150, "date": "2026-06-13", "symbol": "NCC", "timeframe": "Daily", "pattern": "AI Channel Breakout", "patterns": "[\"AI Channel Breakout\"]", "price": 151.69, "sl": 127.58, "target1": 187.86, "target2": 211.97, "target3": 211.97, "rr": 2.5, "vol_ratio": 1.33, "fno": 1, "tv_link": "https://in.tradingview.com/chart/?symbol=NSE:NCC"}, {"id": 5, "date": "2026-06-10", "symbol": "FEDERALBNK", "timeframe": "Monthly", "pattern": "6M Breakout", "patterns": "[\"Monthly: 6M Breakout\"]", "price": 311.1, "sl": 303.35, "target1": 322.73, "target2": 330.49, "target3": 342.12, "rr": 1.5, "vol_ratio": 0.4, "fno": 1, "tv_link": "https://in.tradingview.com/chart/?symbol=NSE:FEDERALBNK"}, {"id": 6, "date": "2026-06-10", "symbol": "RBLBANK", "timeframe": "Monthly", "pattern": "6M Breakout", "patterns": "[\"Weekly: Cup & Handle\", \"Monthly: 6M Breakout\"]", "price": 357.0, "sl": 346.46, "target1": 372.68, "target2": 383.17, "target3": 398.9, "rr": 1.5, "vol_ratio": 1.4, "fno": 1, "tv_link": "https://in.tradingview.com/chart/?symbol=NSE:RBLBANK"}, {"id": 7, "date": "2026-06-10", "symbol": "ZEEL", "timeframe": "Monthly", "pattern": "6M Breakout", "patterns": "[\"Weekly: Cup & Handle\", \"Monthly: 6M Breakout\"]", "price": 102.9, "sl": 97.37, "target1": 111.27, "target2": 116.61, "target3": 125.16, "rr": 1.5, "vol_ratio": 1.0, "fno": 1, "tv_link": "https://in.tradingview.com/chart/?symbol=NSE:ZEEL"}, {"id": 8, "date": "2026-06-10", "symbol": "APOLLOHOSP", "timeframe": "Monthly", "pattern": "6M Breakout", "patterns": "[\"Weekly: Cup & Handle\", \"Monthly: 6M Breakout\"]", "price": 8488.5, "sl": 8321.54, "target1": 8580.88, "target2": 8905.89, "target3": 9156.33, "rr": 0.6, "vol_ratio": 1.0, "fno": 1, "tv_link": "https://in.tradingview.com/chart/?symbol=NSE:APOLLOHOSP"}, {"id": 9, "date": "2026-06-10", "symbol": "WOCKPHARMA", "timeframe": "Weekly", "pattern": "Cup & Handle", "patterns": "[\"Weekly: Cup & Handle\"]", "price": 1833.0, "sl": 1790.35, "target1": 2010.88, "target2": 2129.47, "target3": 2307.36, "rr": 4.2, "vol_ratio": 0.4, "fno": 1, "tv_link": "https://in.tradingview.com/chart/?symbol=NSE:WOCKPHARMA"}, {"id": 10, "date": "2026-06-10", "symbol": "BANDHANBNK", "timeframe": "Weekly", "pattern": "Cup & Handle", "patterns": "[\"Weekly: Cup & Handle\"]", "price": 199.8, "sl": 196.76, "target1": 211.42, "target2": 211.42, "target3": 224.21, "rr": 3.9, "vol_ratio": 0.7, "fno": 1, "tv_link": "https://in.tradingview.com/chart/?symbol=NSE:BANDHANBNK"}, {"id": 11, "date": "2026-06-10", "symbol": "ADANIPOWER", "timeframe": "Weekly", "pattern": "Cup & Handle", "patterns": "[\"Weekly: Cup & Handle\"]", "price": 220.6, "sl": 217.27, "target1": 232.97, "target2": 241.22, "target3": 253.61, "rr": 3.7, "vol_ratio": 0.5, "fno": 1, "tv_link": "https://in.tradingview.com/chart/?symbol=NSE:ADANIPOWER"}, {"id": 12, "date": "2026-06-10", "symbol": "EXIDEIND", "timeframe": "Weekly", "pattern": "Cup & Handle", "patterns": "[\"Weekly: Cup & Handle\"]", "price": 386.4, "sl": 380.55, "target1": 407.75, "target2": 416.42, "target3": 434.46, "rr": 3.7, "vol_ratio": 0.2, "fno": 1, "tv_link": "https://in.tradingview.com/chart/?symbol=NSE:EXIDEIND"}, {"id": 13, "date": "2026-06-10", "symbol": "MANAPPURAM", "timeframe": "Weekly", "pattern": "Cup & Handle", "patterns": "[\"Weekly: Cup & Handle\"]", "price": 288.2, "sl": 283.93, "target1": 303.34, "target2": 313.4, "target3": 328.49, "rr": 3.5, "vol_ratio": 1.4, "fno": 1, "tv_link": "https://in.tradingview.com/chart/?symbol=NSE:MANAPPURAM"}, {"id": 14, "date": "2026-06-10", "symbol": "OFSS", "timeframe": "Weekly", "pattern": "Cup & Handle", "patterns": "[\"Weekly: Cup & Handle\"]", "price": 9470.0, "sl": 9327.95, "target1": 9965.78, "target2": 10531.58, "target3": 10792.08, "rr": 3.5, "vol_ratio": 0.5, "fno": 1, "tv_link": "https://in.tradingview.com/chart/?symbol=NSE:OFSS"}, {"id": 15, "date": "2026-06-10", "symbol": "SAIL", "timeframe": "Weekly", "pattern": "Cup & Handle", "patterns": "[\"Weekly: Cup & Handle\"]", "price": 181.7, "sl": 178.99, "target1": 191.2, "target2": 197.52, "target3": 206.99, "rr": 3.5, "vol_ratio": 0.4, "fno": 1, "tv_link": "https://in.tradingview.com/chart/?symbol=NSE:SAIL"}, {"id": 16, "date": "2026-06-10", "symbol": "CROMPTON", "timeframe": "Weekly", "pattern": "Cup & Handle", "patterns": "[\"Weekly: Cup & Handle\"]", "price": 254.6, "sl": 250.83, "target1": 267.56, "target2": 276.17, "target3": 289.07, "rr": 3.4, "vol_ratio": 0.8, "fno": 1, "tv_link": "https://in.tradingview.com/chart/?symbol=NSE:CROMPTON"}, {"id": 17, "date": "2026-06-10", "symbol": "JSWENERGY", "timeframe": "Weekly", "pattern": "Cup & Handle", "patterns": "[\"Weekly: Cup & Handle\"]", "price": 560.7, "sl": 552.24, "target1": 588.28, "target2": 612.18, "target3": 634.34, "rr": 3.3, "vol_ratio": 0.7, "fno": 1, "tv_link": "https://in.tradingview.com/chart/?symbol=NSE:JSWENERGY"}, {"id": 18, "date": "2026-06-10", "symbol": "SONACOMS", "timeframe": "Weekly", "pattern": "Cup & Handle", "patterns": "[\"Weekly: Cup & Handle\"]", "price": 589.2, "sl": 580.41, "target1": 618.69, "target2": 631.27, "target3": 656.48, "rr": 3.3, "vol_ratio": 1.0, "fno": 1, "tv_link": "https://in.tradingview.com/chart/?symbol=NSE:SONACOMS"}, {"id": 19, "date": "2026-06-10", "symbol": "CESC", "timeframe": "Weekly", "pattern": "Cup & Handle", "patterns": "[\"Weekly: Cup & Handle\"]", "price": 168.2, "sl": 165.62, "target1": 176.51, "target2": 182.05, "target3": 190.36, "rr": 3.2, "vol_ratio": 0.4, "fno": 1, "tv_link": "https://in.tradingview.com/chart/?symbol=NSE:CESC"}, {"id": 20, "date": "2026-06-10", "symbol": "COFORGE", "timeframe": "Weekly", "pattern": "Cup & Handle", "patterns": "[\"Weekly: Cup & Handle\"]", "price": 1402.7, "sl": 1377.69, "target1": 1482.57, "target2": 1546.23, "target3": 1615.68, "rr": 3.2, "vol_ratio": 0.3, "fno": 1, "tv_link": "https://in.tradingview.com/chart/?symbol=NSE:COFORGE"}, {"id": 21, "date": "2026-06-10", "symbol": "ABCAPITAL", "timeframe": "Weekly", "pattern": "Cup & Handle", "patterns": "[\"Weekly: Cup & Handle\"]", "price": 342.7, "sl": 337.56, "target1": 358.75, "target2": 367.95, "target3": 385.5, "rr": 3.1, "vol_ratio": 0.5, "fno": 1, "tv_link": "https://in.tradingview.com/chart/?symbol=NSE:ABCAPITAL"}, {"id": 22, "date": "2026-06-10", "symbol": "LAURUSLABS", "timeframe": "Weekly", "pattern": "Cup & Handle", "patterns": "[\"Weekly: Cup & Handle\"]", "price": 1385.7, "sl": 1364.91, "target1": 1449.71, "target2": 1449.71, "target3": 1521.42, "rr": 3.1, "vol_ratio": 0.7, "fno": 1, "tv_link": "https://in.tradingview.com/chart/?symbol=NSE:LAURUSLABS"}, {"id": 23, "date": "2026-06-10", "symbol": "AARTIIND", "timeframe": "Weekly", "pattern": "Cup & Handle", "patterns": "[\"Weekly: Cup & Handle\"]", "price": 433.6, "sl": 426.33, "target1": 455.67, "target2": 470.35, "target3": 492.37, "rr": 3.0, "vol_ratio": 0.5, "fno": 1, "tv_link": "https://in.tradingview.com/chart/?symbol=NSE:AARTIIND"}, {"id": 24, "date": "2026-06-10", "symbol": "ABB", "timeframe": "Weekly", "pattern": "Cup & Handle", "patterns": "[\"Weekly: Cup & Handle\"]", "price": 6801.0, "sl": 6698.98, "target1": 7103.48, "target2": 7303.3, "target3": 7607.62, "rr": 3.0, "vol_ratio": 1.2, "fno": 1, "tv_link": "https://in.tradingview.com/chart/?symbol=NSE:ABB"}, {"id": 25, "date": "2026-06-10", "symbol": "NTPCGREEN", "timeframe": "Weekly", "pattern": "Cup & Handle", "patterns": "[\"Weekly: Cup & Handle\"]", "price": 98.3, "sl": 96.85, "target1": 102.67, "target2": 105.57, "target3": 109.93, "rr": 3.0, "vol_ratio": 0.5, "fno": 1, "tv_link": "https://in.tradingview.com/chart/?symbol=NSE:NTPCGREEN"}, {"id": 26, "date": "2026-06-10", "symbol": "HINDPETRO", "timeframe": "Weekly", "pattern": "Cup & Handle", "patterns": "[\"Weekly: Cup & Handle\"]", "price": 374.4, "sl": 368.47, "target1": 391.67, "target2": 410.49, "target3": 420.45, "rr": 2.9, "vol_ratio": 0.7, "fno": 1, "tv_link": "https://in.tradingview.com/chart/?symbol=NSE:HINDPETRO"}, {"id": 27, "date": "2026-06-10", "symbol": "USHAMART", "timeframe": "Weekly", "pattern": "Cup & Handle", "patterns": "[\"Weekly: Cup & Handle\"]", "price": 480.6, "sl": 471.55, "target1": 507.04, "target2": 524.86, "target3": 551.02, "rr": 2.9, "vol_ratio": 0.8, "fno": 1, "tv_link": "https://in.tradingview.com/chart/?symbol=NSE:USHAMART"}, {"id": 28, "date": "2026-06-10", "symbol": "IDEA", "timeframe": "Weekly", "pattern": "Cup & Handle", "patterns": "[\"Weekly: Cup & Handle\"]", "price": 13.9, "sl": 13.62, "target1": 14.64, "target2": 15.17, "target3": 15.89, "rr": 2.9, "vol_ratio": 1.2, "fno": 1, "tv_link": "https://in.tradingview.com/chart/?symbol=NSE:IDEA"}, {"id": 29, "date": "2026-06-10", "symbol": "INDUSINDBK", "timeframe": "Weekly", "pattern": "Cup & Handle", "patterns": "[\"Weekly: Cup & Handle\"]", "price": 884.0, "sl": 870.69, "target1": 920.8, "target2": 935.5, "target3": 982.21, "rr": 2.8, "vol_ratio": 1.1, "fno": 1, "tv_link": "https://in.tradingview.com/chart/?symbol=NSE:INDUSINDBK"}, {"id": 30, "date": "2026-06-10", "symbol": "KEI", "timeframe": "Weekly", "pattern": "Cup & Handle", "patterns": "[\"Weekly: Cup & Handle\"]", "price": 5166.5, "sl": 5065.12, "target1": 5448.92, "target2": 5585.34, "target3": 5836.65, "rr": 2.8, "vol_ratio": 0.6, "fno": 1, "tv_link": "https://in.tradingview.com/chart/?symbol=NSE:KEI"}, {"id": 31, "date": "2026-06-10", "symbol": "SJVN", "timeframe": "Weekly", "pattern": "Cup & Handle", "patterns": "[\"Weekly: Cup & Handle\"]", "price": 71.8, "sl": 70.73, "target1": 74.85, "target2": 76.88, "target3": 79.92, "rr": 2.8, "vol_ratio": 0.4, "fno": 1, "tv_link": "https://in.tradingview.com/chart/?symbol=NSE:SJVN"}, {"id": 32, "date": "2026-06-10", "symbol": "TIINDIA", "timeframe": "Weekly", "pattern": "Cup & Handle", "patterns": "[\"Weekly: Cup & Handle\"]", "price": 3062.3, "sl": 2999.67, "target1": 3233.75, "target2": 3325.64, "target3": 3483.64, "rr": 2.7, "vol_ratio": 0.6, "fno": 1, "tv_link": "https://in.tradingview.com/chart/?symbol=NSE:TIINDIA"}, {"id": 33, "date": "2026-06-10", "symbol": "ADANIENT", "timeframe": "Weekly", "pattern": "Cup & Handle", "patterns": "[\"Weekly: Cup & Handle\"]", "price": 2931.1, "sl": 2887.13, "target1": 3044.5, "target2": 3143.52, "target3": 3270.97, "rr": 2.6, "vol_ratio": 0.5, "fno": 1, "tv_link": "https://in.tradingview.com/chart/?symbol=NSE:ADANIENT"}, {"id": 34, "date": "2026-06-10", "symbol": "LICHSGFIN", "timeframe": "Weekly", "pattern": "Cup & Handle", "patterns": "[\"Weekly: Cup & Handle\"]", "price": 541.0, "sl": 532.87, "target1": 562.13, "target2": 578.05, "target3": 598.32, "rr": 2.6, "vol_ratio": 0.3, "fno": 1, "tv_link": "https://in.tradingview.com/chart/?symbol=NSE:LICHSGFIN"}, {"id": 35, "date": "2026-06-10", "symbol": "PETRONET", "timeframe": "Weekly", "pattern": "Cup & Handle", "patterns": "[\"Weekly: Cup & Handle\"]", "price": 268.3, "sl": 263.83, "target1": 279.4, "target2": 282.83, "target3": 292.66, "rr": 2.5, "vol_ratio": 1.2, "fno": 1, "tv_link": "https://in.tradingview.com/chart/?symbol=NSE:PETRONET"}, {"id": 36, "date": "2026-06-10", "symbol": "AWL", "timeframe": "Weekly", "pattern": "Cup & Handle", "patterns": "[\"Weekly: Cup & Handle\"]", "price": 187.1, "sl": 183.75, "target1": 195.32, "target2": 202.76, "target3": 207.96, "rr": 2.4, "vol_ratio": 1.9, "fno": 1, "tv_link": "https://in.tradingview.com/chart/?symbol=NSE:AWL"}, {"id": 37, "date": "2026-06-10", "symbol": "NUVOCO", "timeframe": "Weekly", "pattern": "Cup & Handle", "patterns": "[\"Weekly: Cup & Handle\"]", "price": 309.7, "sl": 302.04, "target1": 327.79, "target2": 339.85, "target3": 357.94, "rr": 2.4, "vol_ratio": 0.4, "fno": 1, "tv_link": "https://in.tradingview.com/chart/?symbol=NSE:NUVOCO"}, {"id": 38, "date": "2026-06-10", "symbol": "JSWSTEEL", "timeframe": "Weekly", "pattern": "Cup & Handle", "patterns": "[\"Weekly: Cup & Handle\"]", "price": 1269.8, "sl": 1245.82, "target1": 1321.36, "target2": 1321.36, "target3": 1376.73, "rr": 2.2, "vol_ratio": 1.6, "fno": 1, "tv_link": "https://in.tradingview.com/chart/?symbol=NSE:JSWSTEEL"}, {"id": 39, "date": "2026-06-10", "symbol": "GRASIM", "timeframe": "Weekly", "pattern": "Cup & Handle", "patterns": "[\"Weekly: Cup & Handle\"]", "price": 3071.2, "sl": 3019.3, "target1": 3181.51, "target2": 3181.51, "target3": 3320.8, "rr": 2.1, "vol_ratio": 0.8, "fno": 1, "tv_link": "https://in.tradingview.com/chart/?symbol=NSE:GRASIM"}, {"id": 40, "date": "2026-06-10", "symbol": "POLICYBZR", "timeframe": "Weekly", "pattern": "Cup & Handle", "patterns": "[\"Weekly: Cup & Handle\"]", "price": 1509.6, "sl": 1464.42, "target1": 1592.87, "target2": 1648.38, "target3": 1731.66, "rr": 1.8, "vol_ratio": 0.9, "fno": 1, "tv_link": "https://in.tradingview.com/chart/?symbol=NSE:POLICYBZR"}, {"id": 41, "date": "2026-06-10", "symbol": "TECHM", "timeframe": "Weekly", "pattern": "Cup & Handle", "patterns": "[\"Weekly: Cup & Handle\"]", "price": 1478.9, "sl": 1441.86, "target1": 1546.33, "target2": 1581.06, "target3": 1658.7, "rr": 1.8, "vol_ratio": 0.4, "fno": 1, "tv_link": "https://in.tradingview.com/chart/?symbol=NSE:TECHM"}, {"id": 42, "date": "2026-06-10", "symbol": "TRENT", "timeframe": "Weekly", "pattern": "Cup & Handle", "patterns": "[\"Weekly: Cup & Handle\"]", "price": 2754.7, "sl": 2688.58, "target1": 2876.01, "target2": 2953.89, "target3": 3073.41, "rr": 1.8, "vol_ratio": 1.4, "fno": 1, "tv_link": "https://in.tradingview.com/chart/?symbol=NSE:TRENT"}, {"id": 43, "date": "2026-06-10", "symbol": "HAL", "timeframe": "Weekly", "pattern": "Cup & Handle", "patterns": "[\"Weekly: Cup & Handle\"]", "price": 4219.2, "sl": 4121.41, "target1": 4383.51, "target2": 4493.05, "target3": 4657.36, "rr": 1.7, "vol_ratio": 0.5, "fno": 1, "tv_link": "https://in.tradingview.com/chart/?symbol=NSE:HAL"}, {"id": 44, "date": "2026-06-10", "symbol": "POLYCAB", "timeframe": "Weekly", "pattern": "Cup & Handle", "patterns": "[\"Weekly: Cup & Handle\"]", "price": 9523.5, "sl": 9369.15, "target1": 9783.83, "target2": 10067.0, "target3": 10393.1, "rr": 1.7, "vol_ratio": 1.5, "fno": 1, "tv_link": "https://in.tradingview.com/chart/?symbol=NSE:POLYCAB"}, {"id": 45, "date": "2026-06-10", "symbol": "DEEPAKNTR", "timeframe": "Weekly", "pattern": "Cup & Handle", "patterns": "[\"Weekly: Cup & Handle\"]", "price": 1664.7, "sl": 1624.05, "target1": 1731.3, "target2": 1799.18, "target3": 1879.87, "rr": 1.6, "vol_ratio": 0.5, "fno": 1, "tv_link": "https://in.tradingview.com/chart/?symbol=NSE:DEEPAKNTR"}, {"id": 46, "date": "2026-06-10", "symbol": "BOSCHLTD", "timeframe": "Weekly", "pattern": "Cup & Handle", "patterns": "[\"Weekly: Cup & Handle\"]", "price": 37790.0, "sl": 36689.27, "target1": 39441.09, "target2": 40541.81, "target3": 42192.9, "rr": 1.5, "vol_ratio": 1.1, "fno": 1, "tv_link": "https://in.tradingview.com/chart/?symbol=NSE:BOSCHLTD"}, {"id": 47, "date": "2026-06-10", "symbol": "COLPAL", "timeframe": "Weekly", "pattern": "Cup & Handle", "patterns": "[\"Weekly: Cup & Handle\"]", "price": 2056.3, "sl": 2009.22, "target1": 2126.92, "target2": 2186.8, "target3": 2244.63, "rr": 1.5, "vol_ratio": 2.5, "fno": 1, "tv_link": "https://in.tradingview.com/chart/?symbol=NSE:COLPAL"}, {"id": 48, "date": "2026-06-10", "symbol": "FORTIS", "timeframe": "Weekly", "pattern": "Cup & Handle", "patterns": "[\"Weekly: Cup & Handle\"]", "price": 989.0, "sl": 963.62, "target1": 1027.07, "target2": 1052.46, "target3": 1090.53, "rr": 1.5, "vol_ratio": 1.3, "fno": 1, "tv_link": "https://in.tradingview.com/chart/?symbol=NSE:FORTIS"}, {"id": 49, "date": "2026-06-10", "symbol": "GAIL", "timeframe": "Weekly", "pattern": "Cup & Handle", "patterns": "[\"Weekly: Cup & Handle\"]", "price": 168.0, "sl": 163.79, "target1": 174.35, "target2": 178.57, "target3": 184.91, "rr": 1.5, "vol_ratio": 0.9, "fno": 1, "tv_link": "https://in.tradingview.com/chart/?symbol=NSE:GAIL"}, {"id": 50, "date": "2026-06-10", "symbol": "INDHOTEL", "timeframe": "Weekly", "pattern": "Cup & Handle", "patterns": "[\"Weekly: Cup & Handle\"]", "price": 665.8, "sl": 649.32, "target1": 690.65, "target2": 707.18, "target3": 731.97, "rr": 1.5, "vol_ratio": 1.0, "fno": 1, "tv_link": "https://in.tradingview.com/chart/?symbol=NSE:INDHOTEL"}, {"id": 51, "date": "2026-06-10", "symbol": "INDIGO", "timeframe": "Weekly", "pattern": "Cup & Handle", "patterns": "[\"Weekly: Cup & Handle\"]", "price": 4524.9, "sl": 4397.82, "target1": 4715.53, "target2": 4842.61, "target3": 5033.24, "rr": 1.5, "vol_ratio": 0.6, "fno": 1, "tv_link": "https://in.tradingview.com/chart/?symbol=NSE:INDIGO"}, {"id": 52, "date": "2026-06-10", "symbol": "LT", "timeframe": "Weekly", "pattern": "Cup & Handle", "patterns": "[\"Weekly: Cup & Handle\"]", "price": 3917.5, "sl": 3844.42, "target1": 4029.58, "target2": 4107.36, "target3": 4216.39, "rr": 1.5, "vol_ratio": 1.1, "fno": 1, "tv_link": "https://in.tradingview.com/chart/?symbol=NSE:LT"}, {"id": 53, "date": "2026-06-10", "symbol": "RECLTD", "timeframe": "Weekly", "pattern": "Cup & Handle", "patterns": "[\"Weekly: Cup & Handle\"]", "price": 348.8, "sl": 340.46, "target1": 361.31, "target2": 369.65, "target3": 382.16, "rr": 1.5, "vol_ratio": 0.8, "fno": 1, "tv_link": "https://in.tradingview.com/chart/?symbol=NSE:RECLTD"}, {"id": 54, "date": "2026-06-10", "symbol": "TATACOMM", "timeframe": "Weekly", "pattern": "Cup & Handle", "patterns": "[\"Daily: Bull Flag\", \"Weekly: Cup & Handle\"]", "price": 1978.6, "sl": 1902.76, "target1": 2092.36, "target2": 2168.2, "target3": 2281.96, "rr": 1.5, "vol_ratio": 0.6, "fno": 1, "tv_link": "https://in.tradingview.com/chart/?symbol=NSE:TATACOMM"}, {"id": 55, "date": "2026-06-10", "symbol": "BERGEPAINT", "timeframe": "Weekly", "pattern": "Cup & Handle", "patterns": "[\"Weekly: Cup & Handle\"]", "price": 516.7, "sl": 499.58, "target1": 537.65, "target2": 559.5, "target3": 585.17, "rr": 1.2, "vol_ratio": 1.2, "fno": 1, "tv_link": "https://in.tradingview.com/chart/?symbol=NSE:BERGEPAINT"}, {"id": 56, "date": "2026-06-10", "symbol": "LALPATHLAB", "timeframe": "Weekly", "pattern": "Cup & Handle", "patterns": "[\"Weekly: Cup & Handle\"]", "price": 1568.7, "sl": 1516.5, "target1": 1629.91, "target2": 1711.3, "target3": 1777.51, "rr": 1.2, "vol_ratio": 0.7, "fno": 1, "tv_link": "https://in.tradingview.com/chart/?symbol=NSE:LALPATHLAB"}, {"id": 57, "date": "2026-06-10", "symbol": "IGL", "timeframe": "Weekly", "pattern": "Cup & Handle", "patterns": "[\"Weekly: Cup & Handle\"]", "price": 162.2, "sl": 159.0, "target1": 165.85, "target2": 173.15, "target3": 179.73, "rr": 1.2, "vol_ratio": 0.3, "fno": 1, "tv_link": "https://in.tradingview.com/chart/?symbol=NSE:IGL"}, {"id": 58, "date": "2026-06-10", "symbol": "AUROPHARMA", "timeframe": "Weekly", "pattern": "Cup & Handle", "patterns": "[\"Weekly: Cup & Handle\"]", "price": 1453.6, "sl": 1422.78, "target1": 1489.02, "target2": 1542.25, "target3": 1594.71, "rr": 1.1, "vol_ratio": 0.9, "fno": 1, "tv_link": "https://in.tradingview.com/chart/?symbol=NSE:AUROPHARMA"}, {"id": 59, "date": "2026-06-10", "symbol": "ADANIGREEN", "timeframe": "Weekly", "pattern": "Cup & Handle", "patterns": "[\"Weekly: Cup & Handle\"]", "price": 1483.0, "sl": 1428.36, "target1": 1537.08, "target2": 1619.61, "target3": 1701.58, "rr": 1.0, "vol_ratio": 0.7, "fno": 1, "tv_link": "https://in.tradingview.com/chart/?symbol=NSE:ADANIGREEN"}, {"id": 60, "date": "2026-06-10", "symbol": "NYKAA", "timeframe": "Weekly", "pattern": "Cup & Handle", "patterns": "[\"Weekly: Cup & Handle\"]", "price": 262.4, "sl": 256.03, "target1": 269.05, "target2": 284.17, "target3": 290.69, "rr": 1.0, "vol_ratio": 1.8, "fno": 1, "tv_link": "https://in.tradingview.com/chart/?symbol=NSE:NYKAA"}, {"id": 61, "date": "2026-06-10", "symbol": "PAGEIND", "timeframe": "Weekly", "pattern": "Cup & Handle", "patterns": "[\"Weekly: Cup & Handle\"]", "price": 37955.0, "sl": 36992.13, "target1": 38894.55, "target2": 40129.79, "target3": 42160.84, "rr": 1.0, "vol_ratio": 0.5, "fno": 1, "tv_link": "https://in.tradingview.com/chart/?symbol=NSE:PAGEIND"}, {"id": 62, "date": "2026-06-10", "symbol": "PHOENIXLTD", "timeframe": "Weekly", "pattern": "Cup & Handle", "patterns": "[\"Weekly: Cup & Handle\"]", "price": 1765.7, "sl": 1715.45, "target1": 1810.2, "target2": 1891.32, "target3": 1966.7, "rr": 0.9, "vol_ratio": 1.6, "fno": 1, "tv_link": "https://in.tradingview.com/chart/?symbol=NSE:PHOENIXLTD"}, {"id": 63, "date": "2026-06-10", "symbol": "STARHEALTH", "timeframe": "Weekly", "pattern": "Cup & Handle", "patterns": "[\"Weekly: Cup & Handle\"]", "price": 524.4, "sl": 510.59, "target1": 536.75, "target2": 558.93, "target3": 579.65, "rr": 0.9, "vol_ratio": 0.8, "fno": 1, "tv_link": "https://in.tradingview.com/chart/?symbol=NSE:STARHEALTH"}, {"id": 64, "date": "2026-06-10", "symbol": "ASIANPAINT", "timeframe": "Weekly", "pattern": "Cup & Handle", "patterns": "[\"Weekly: Cup & Handle\"]", "price": 2715.1, "sl": 2655.09, "target1": 2764.91, "target2": 2865.11, "target3": 2955.12, "rr": 0.8, "vol_ratio": 1.1, "fno": 1, "tv_link": "https://in.tradingview.com/chart/?symbol=NSE:ASIANPAINT"}, {"id": 65, "date": "2026-06-10", "symbol": "UCOBANK", "timeframe": "Weekly", "pattern": "Cup & Handle", "patterns": "[\"Weekly: Cup & Handle\"]", "price": 25.8, "sl": 25.14, "target1": 26.21, "target2": 27.26, "target3": 28.17, "rr": 0.8, "vol_ratio": 1.9, "fno": 1, "tv_link": "https://in.tradingview.com/chart/?symbol=NSE:UCOBANK"}, {"id": 66, "date": "2026-06-10", "symbol": "IDFCFIRSTB", "timeframe": "Weekly", "pattern": "Cup & Handle", "patterns": "[\"Weekly: Cup & Handle\"]", "price": 73.0, "sl": 71.28, "target1": 74.13, "target2": 77.27, "target3": 79.84, "rr": 0.7, "vol_ratio": 0.8, "fno": 1, "tv_link": "https://in.tradingview.com/chart/?symbol=NSE:IDFCFIRSTB"}, {"id": 67, "date": "2026-06-10", "symbol": "PIDILITIND", "timeframe": "Weekly", "pattern": "Cup & Handle", "patterns": "[\"Weekly: Cup & Handle\"]", "price": 1506.5, "sl": 1475.64, "target1": 1528.12, "target2": 1583.66, "target3": 1629.95, "rr": 0.7, "vol_ratio": 2.2, "fno": 1, "tv_link": "https://in.tradingview.com/chart/?symbol=NSE:PIDILITIND"}, {"id": 68, "date": "2026-06-10", "symbol": "ADANIPORTS", "timeframe": "Weekly", "pattern": "Cup & Handle", "patterns": "[\"Weekly: Cup & Handle\"]", "price": 1821.2, "sl": 1778.6, "target1": 1848.51, "target2": 1927.71, "target3": 1991.61, "rr": 0.6, "vol_ratio": 1.3, "fno": 1, "tv_link": "https://in.tradingview.com/chart/?symbol=NSE:ADANIPORTS"}, {"id": 1, "date": "2026-05-09", "symbol": "AXISBANK", "timeframe": "Weekly", "pattern": "Cup & Handle", "patterns": "[\"Weekly: Cup & Handle\"]", "price": NaN, "sl": NaN, "target1": NaN, "target2": NaN, "target3": NaN, "rr": NaN, "vol_ratio": 0.6, "fno": 1, "tv_link": "https://in.tradingview.com/chart/?symbol=NSE:AXISBANK"}, {"id": 2, "date": "2026-05-09", "symbol": "DMART", "timeframe": "Weekly", "pattern": "Cup & Handle", "patterns": "[\"Weekly: Cup & Handle\"]", "price": NaN, "sl": NaN, "target1": NaN, "target2": NaN, "target3": NaN, "rr": NaN, "vol_ratio": 1.3, "fno": 1, "tv_link": "https://in.tradingview.com/chart/?symbol=NSE:DMART"}, {"id": 3, "date": "2026-05-09", "symbol": "ATUL", "timeframe": "Weekly", "pattern": "Cup & Handle", "patterns": "[\"Weekly: Cup & Handle\"]", "price": NaN, "sl": NaN, "target1": NaN, "target2": NaN, "target3": NaN, "rr": NaN, "vol_ratio": 0.6, "fno": 1, "tv_link": "https://in.tradingview.com/chart/?symbol=NSE:ATUL"}, {"id": 4, "date": "2026-05-09", "symbol": "IPCALAB", "timeframe": "Weekly", "pattern": "20W Breakout", "patterns": "[\"Weekly: 20W Breakout\"]", "price": NaN, "sl": NaN, "target1": NaN, "target2": NaN, "target3": NaN, "rr": NaN, "vol_ratio": 0.6, "fno": 1, "tv_link": "https://in.tradingview.com/chart/?symbol=NSE:IPCALAB"}]